cmstp/__init__.py
cmstp/main.py
cmstp/cli/core.py
cmstp/cli/info.py
cmstp/cli/setup.py
cmstp/cli/utils.py
cmstp/config/README.md
cmstp/config/default.yaml
cmstp/config/enabled.yaml
cmstp/config/configure/configure_bashrc.bash
cmstp/config/configure/configure_filestructure.yaml
cmstp/config/configure/configure_pinned_apps.txt
cmstp/config/configure/configure_vscode_keybindings.jsonc
cmstp/config/install/install_apt_packages.txt
cmstp/config/install/install_conda_environments.jsonc
cmstp/config/install/install_docker_images.jsonc
cmstp/config/install/install_flatpak_packages.txt
cmstp/config/install/install_js_repositories.txt
cmstp/config/install/install_npm_packages.txt
cmstp/config/install/install_pip_environments.jsonc
cmstp/config/install/install_pipx_packages.txt
cmstp/config/install/install_snap_packages.txt
cmstp/config/install/install_vscode_extensions.txt
cmstp/core/logger.py
cmstp/core/scheduler.py
cmstp/core/task_processor.py
cmstp/scripts/bash/configure/checks.bash
cmstp/scripts/bash/configure/simple_configurations.bash
cmstp/scripts/bash/helpers/_interface.bash
cmstp/scripts/bash/helpers/helpers.bash
cmstp/scripts/bash/helpers/marking.bash
cmstp/scripts/bash/helpers/processing.bash
cmstp/scripts/bash/install/checks.bash
cmstp/scripts/bash/install/conda.bash
cmstp/scripts/bash/install/docker.bash
cmstp/scripts/bash/install/isaac.bash
cmstp/scripts/bash/install/nvidia.bash
cmstp/scripts/bash/install/ros.bash
cmstp/scripts/bash/install/simple_installations.bash
cmstp/scripts/bash/uninstall/checks.bash
cmstp/scripts/bash/uninstall/simple_uninstallations.bash
cmstp/scripts/python/configure/checks.py
cmstp/scripts/python/configure/simple_configurations.py
cmstp/scripts/python/helpers/_interface.py
cmstp/scripts/python/helpers/common.py
cmstp/scripts/python/helpers/processing.py
cmstp/scripts/python/install/checks.py
cmstp/scripts/python/install/environments.py
cmstp/scripts/python/install/js.py
cmstp/scripts/python/install/package_managers.py
cmstp-1.3.1.dist-info/licenses/LICENSE
cmstp-1.3.1.dist-info/METADATA
cmstp-1.3.1.dist-info/WHEEL
cmstp-1.3.1.dist-info/entry_points.txt
cmstp-1.3.1.dist-info/top_level.txt
cmstp-1.3.1.dist-info/RECORD
